structools/__init__.py
structools/backtest/backtester.py
structools/launch.py
structools/products/__init__.py
structools/products/autocalls.py
structools/products/basic_products.py
structools/streamlit/__init__.py
structools/streamlit/app_main.py
structools/streamlit/pages/__init__.py
structools/streamlit/pages/backtester.py
structools/streamlit/pages/home.py
structools/streamlit/pages/product_builder.py
structools/streamlit/pages/underlying_builder.py
structools/streamlit/template.py
structools/test.py
structools/tools/__init__.py
structools/tools/date_tools.py
structools/tools/market.py
structools/tools/timer.py
structools-0.19.3.dist-info/LICENSE
structools-0.19.3.dist-info/METADATA
structools-0.19.3.dist-info/WHEEL
structools-0.19.3.dist-info/RECORD
